{
 "copart":{"	NJ - GLASSBORO EAST ":[
                     ["NJ", "1000"],
                     ["TX", "2000"],
                     ["GA", "3000"],
                     ["FL", "4000"],
                     ["CA", "5000"],
                     ["CAN", "6000"],
                     ["other", "0"]],
          "CA - RANCHO CUCAMONGA":[
                     ["NJ", "1000"],
                     ["TX", "2000"],
                     ["GA", "3000"],
                     ["FL", "4000"],
                     ["CA", "5000"],
                     ["CAN", "6000"],
                     ["other", "0"]
            ],
          }
  "iaai":{"	NJ - GLASSBORO EAST ":[
                     ["NJ", "1000"],
                     ["TX", "2000"],
                     ["GA", "3000"],
                     ["FL", "4000"],
                     ["CA", "5000"],
                     ["CAN", "6000"],
                     ["other", "0"]],
          "CA - RANCHO CUCAMONGA":[
                     ["NJ", "1000"],
                     ["TX", "2000"],
                     ["GA", "3000"],
                     ["FL", "4000"],
                     ["CA", "5000"],
                     ["CAN", "6000"],
                     ["other", "0"]
            ] 
          }
}